academy_tester/FileReadOutputRead.py
academy_tester/__init__.py
academy_tester/ast_node_types.py
academy_tester/test_utils.py
academy_tester/tester.py
academy_tester-2.2.0.dist-info/licenses/LICENSE
academy_tester-2.2.0.dist-info/METADATA
academy_tester-2.2.0.dist-info/WHEEL
academy_tester-2.2.0.dist-info/top_level.txt
academy_tester-2.2.0.dist-info/RECORD
