Metadata-Version: 2.4
Name: academy-tester
Version: 2.2.0
Summary: Package to help test tasks in the PyCharm JetBrains Academy plugin
Author-email: Alastair Thomson <alastairw.thomson@gmail.com>
License-Expression: MIT
Project-URL: Homepage, https://github.com/marguhrita/academy-tester
Project-URL: Issues, https://github.com/marguhrita/academy-tester/issues
Classifier: Programming Language :: Python :: 3
Classifier: Operating System :: OS Independent
Requires-Python: >=3.9
License-File: LICENSE
Dynamic: license-file
